setup.cfg
setup.py
pybdd/__init__.py
pybdd.egg-info/PKG-INFO
pybdd.egg-info/SOURCES.txt
pybdd.egg-info/dependency_links.txt
pybdd.egg-info/not-zip-safe
pybdd.egg-info/top_level.txt