Metadata-Version: 1.1
Name: pybdd
Version: 0.0.2
Summary: This is test framework for BDD
Home-page: https://github.com/HarshadKavathiya/pybdd
Author: Harshad Kavathiya
Author-email: harshad3011@gmail.com
License: MIT
Download-URL: https://github.com/HarshadKavathiya/pybdd/archive/master.tar.gz
Keywords: bdd,testing,logging,bdd,cucumber
Platform: UNKNOWN
